{
    "packages": [],
    "includes": {
        "include/all$fa94ef90f22c91a9bb39283c63e6838c87402d8b.json": {
            "sha1": "fa94ef90f22c91a9bb39283c63e6838c87402d8b"
        }
    },
    "metadata-url": "/p2/%package%.json",
    "available-packages": [
        "auxiliary/rpage",
        "blueimp/gallery",
        "blueimp/jquery-file-upload",
        "dangrossman/bootstrap-daterangepicker",
        "derek-watson/jsuri",
        "ingenerator/chrome-mink-driver",
        "ingenerator/cloud-tasks-wrapper",
        "ingenerator/content-snippets",
        "ingenerator/form",
        "ingenerator/image-processing",
        "ingenerator/kohana-core",
        "ingenerator/kohana-dependencies",
        "ingenerator/kohana-extras",
        "ingenerator/no-robloach-component-installer",
        "ingenerator/warden-auth",
        "ingenerator/warden-core",
        "ingenerator/warden-persistence-doctrine",
        "ingenerator/warden-ui-kohana",
        "ingenerator/warden-validator-symfony",
        "mailcheck/mailcheck",
        "makeusabrew/bootbox",
        "markgx/jquery-check-all",
        "mohsen1/json-formatter-js",
        "nostalgiaz/bootstrap-switch",
        "rubaxa/sortable",
        "stefanpenner/es6-promise",
        "tristen/tablesort",
        "yapapaya/jquery-cloneya"
    ]
}
